jcalendar/__init__.py
jcalendar/calendar.py
jcalendar-0.1.3.dist-info/LICENSE
jcalendar-0.1.3.dist-info/METADATA
jcalendar-0.1.3.dist-info/WHEEL
jcalendar-0.1.3.dist-info/top_level.txt
jcalendar-0.1.3.dist-info/RECORD
