Metadata-Version: 2.1
Name: jcalendar
Version: 0.1.3
Summary: Jalali calendar binding for python
Home-page: https://github.com/IKermani/jcalendar
Author: Iman Kermani
Author-email: imankermani97@outlook.com
License: UNKNOWN
Project-URL: Bug Tracker, https://github.com/IKermani/jcalendar/issues
Platform: UNKNOWN
Classifier: Programming Language :: Python :: 3
Classifier: Programming Language :: Python :: 3.5
Classifier: Programming Language :: Python :: 3.6
Classifier: Programming Language :: Python :: 3.7
Classifier: Programming Language :: Python :: 3.8
Classifier: Programming Language :: Python :: 3.9
Classifier: License :: OSI Approved :: MIT License
Classifier: Operating System :: OS Independent
License-File: LICENSE
